rl_bot_model/__init__.py
rl_bot_model/arguments.py
rl_bot_model/distributions.py
rl_bot_model/model.py
rl_bot_model/utils.py
rl_bot_model-0.0.4.dist-info/LICENSE
rl_bot_model-0.0.4.dist-info/METADATA
rl_bot_model-0.0.4.dist-info/WHEEL
rl_bot_model-0.0.4.dist-info/top_level.txt
rl_bot_model-0.0.4.dist-info/RECORD
